leda_python/__init__.py
leda_python/deviceMbus.py
leda_python/json_coder.py
leda_python/leda.py
leda_python/ledaException.py
leda_python/mbus.py
leda_python/mbusConfig.py
lethingaccesssdk/__init__.py
lethingaccesssdk/thing_access.py
lethingaccesssdk-1.2.dist-info/DESCRIPTION.rst
lethingaccesssdk-1.2.dist-info/METADATA
lethingaccesssdk-1.2.dist-info/RECORD
lethingaccesssdk-1.2.dist-info/WHEEL
lethingaccesssdk-1.2.dist-info/entry_points.txt
lethingaccesssdk-1.2.dist-info/metadata.json
lethingaccesssdk-1.2.dist-info/top_level.txt
